{
    "@odata.context": "/redfish/v1/$metadata#DellCertificate.DellCertificate",
    "@odata.id": "/redfish/v1/Systems/System.Embedded.1/SecureBoot/Oem/Dell/Certificates/DBX/StdSecbootpolicy.75",
    "@odata.type": "#DellCertificate.v1_0_1.DellCertificate",
    "CertificateSubtype": "SHA256",
    "CertificateType": "DBX",
    "Description": "SecureBoot Certificate",
    "Id": "StdSecbootpolicy.75",
    "Name": "SecureBoot Certificate",
    "SecureBootPolicy": "Standard",
    "Hash": "FE63A84F782CC9D3FCF2CCF9FC11FBD03760878758D26285ED12669BDC6E6D01"
}