{
    "@odata.context": "/redfish/v1/$metadata#LogEntryCollection.LogEntryCollection",
    "@odata.id": "/redfish/v1/Managers/iDRAC.Embedded.1/LogServices/Lclog/Entries",
    "@odata.type": "#LogEntryCollection.LogEntryCollection",
    "Description": "LC Logs for this manager",
    "Members": [
        {
            "@odata.id": "/redfish/v1/Managers/iDRAC.Embedded.1/LogServices/Lclog/Entries/374275",
            "@odata.type": "#LogEntry.v1_6_1.LogEntry",
            "Created": "2022-10-25T06:56:33-05:00",
            "Description": "Log Entry 374275",
            "EntryType": "Oem",
            "Id": "374275",
            "Links": {
                "OriginOfCondition": {
                    "@odata.id": "/redfish/v1/Managers/iDRAC.Embedded.1"
                }
            },
            "Message": "Successfully logged in using root, from 10.29.152.130 and REDFISH.",
            "MessageArgs": [
                "root",
                "10.29.152.130",
                "REDFISH"
            ],
            "MessageArgs@odata.count": 3,
            "MessageId": "USR0030",
            "Name": "Log Entry 374275",
            "Oem": {
                "Dell": {
                    "@odata.type": "#DellLCLogEntry.v1_0_0.DellLCLogEntry",
                    "Category": "Audit",
                    "Comment": null,
                    "LastUpdatedByUser": null
                }
            },
            "OemRecordFormat": "Dell",
            "Severity": "OK"
        },
        {
            "@odata.id": "/redfish/v1/Managers/iDRAC.Embedded.1/LogServices/Lclog/Entries/374274",
            "@odata.type": "#LogEntry.v1_6_1.LogEntry",
            "Created": "2022-10-25T06:56:33-05:00",
            "Description": "Log Entry 374274",
            "EntryType": "Oem",
            "Id": "374274",
            "Links": {
                "OriginOfCondition": {
                    "@odata.id": "/redfish/v1/Managers/iDRAC.Embedded.1"
                }
            },
            "Message": "The session for engineer from 10.193.28.213 using REDFISH is logged off.",
            "MessageArgs": [
                "engineer",
                "10.193.28.213",
                "REDFISH"
            ],
            "MessageArgs@odata.count": 3,
            "MessageId": "USR0032",
            "Name": "Log Entry 374274",
            "Oem": {
                "Dell": {
                    "@odata.type": "#DellLCLogEntry.v1_0_0.DellLCLogEntry",
                    "Category": "Audit",
                    "Comment": null,
                    "LastUpdatedByUser": null
                }
            },
            "OemRecordFormat": "Dell",
            "Severity": "OK"
        },
        {
            "@odata.id": "/redfish/v1/Managers/iDRAC.Embedded.1/LogServices/Lclog/Entries/374273",
            "@odata.type": "#LogEntry.v1_6_1.LogEntry",
            "Created": "2022-10-25T06:56:32-05:00",
            "Description": "Log Entry 374273",
            "EntryType": "Oem",
            "Id": "374273",
            "Links": {
                "OriginOfCondition": {
                    "@odata.id": "/redfish/v1/Managers/iDRAC.Embedded.1"
                }
            },
            "Message": "The session for root from 10.29.152.130 using REDFISH is logged off.",
            "MessageArgs": [
                "root",
                "10.29.152.130",
                "REDFISH"
            ],
            "MessageArgs@odata.count": 3,
            "MessageId": "USR0032",
            "Name": "Log Entry 374273",
            "Oem": {
                "Dell": {
                    "@odata.type": "#DellLCLogEntry.v1_0_0.DellLCLogEntry",
                    "Category": "Audit",
                    "Comment": null,
                    "LastUpdatedByUser": null
                }
            },
            "OemRecordFormat": "Dell",
            "Severity": "OK"
        },
        {
            "@odata.id": "/redfish/v1/Managers/iDRAC.Embedded.1/LogServices/Lclog/Entries/374272",
            "@odata.type": "#LogEntry.v1_6_1.LogEntry",
            "Created": "2022-10-25T06:56:32-05:00",
            "Description": "Log Entry 374272",
            "EntryType": "Oem",
            "Id": "374272",
            "Links": {},
            "Message": "The previous log entry was repeated 1 times.",
            "MessageArgs": [
                "1"
            ],
            "MessageArgs@odata.count": 1,
            "MessageId": "LOG007",
            "Name": "Log Entry 374272",
            "Oem": {
                "Dell": {
                    "@odata.type": "#DellLCLogEntry.v1_0_0.DellLCLogEntry",
                    "Category": "Audit",
                    "Comment": null,
                    "LastUpdatedByUser": null
                }
            },
            "OemRecordFormat": "Dell",
            "Severity": "OK"
        },
        {
            "@odata.id": "/redfish/v1/Managers/iDRAC.Embedded.1/LogServices/Lclog/Entries/374271",
            "@odata.type": "#LogEntry.v1_6_1.LogEntry",
            "Created": "2022-10-25T06:51:26-05:00",
            "Description": "Log Entry 374271",
            "EntryType": "Oem",
            "Id": "374271",
            "Links": {
                "OriginOfCondition": {
                    "@odata.id": "/redfish/v1/Managers/iDRAC.Embedded.1"
                }
            },
            "Message": "Successfully logged in using engineer, from 10.193.28.213 and REDFISH.",
            "MessageArgs": [
                "engineer",
                "10.193.28.213",
                "REDFISH"
            ],
            "MessageArgs@odata.count": 3,
            "MessageId": "USR0030",
            "Name": "Log Entry 374271",
            "Oem": {
                "Dell": {
                    "@odata.type": "#DellLCLogEntry.v1_0_0.DellLCLogEntry",
                    "Category": "Audit",
                    "Comment": null,
                    "LastUpdatedByUser": null
                }
            },
            "OemRecordFormat": "Dell",
            "Severity": "OK"
        },
        {
            "@odata.id": "/redfish/v1/Managers/iDRAC.Embedded.1/LogServices/Lclog/Entries/374270",
            "@odata.type": "#LogEntry.v1_6_1.LogEntry",
            "Created": "2022-10-25T06:51:25-05:00",
            "Description": "Log Entry 374270",
            "EntryType": "Oem",
            "Id": "374270",
            "Links": {
                "OriginOfCondition": {
                    "@odata.id": "/redfish/v1/Managers/iDRAC.Embedded.1"
                }
            },
            "Message": "Successfully logged in using root, from 10.29.152.130 and REDFISH.",
            "MessageArgs": [
                "root",
                "10.29.152.130",
                "REDFISH"
            ],
            "MessageArgs@odata.count": 3,
            "MessageId": "USR0030",
            "Name": "Log Entry 374270",
            "Oem": {
                "Dell": {
                    "@odata.type": "#DellLCLogEntry.v1_0_0.DellLCLogEntry",
                    "Category": "Audit",
                    "Comment": null,
                    "LastUpdatedByUser": null
                }
            },
            "OemRecordFormat": "Dell",
            "Severity": "OK"
        },
        {
            "@odata.id": "/redfish/v1/Managers/iDRAC.Embedded.1/LogServices/Lclog/Entries/374269",
            "@odata.type": "#LogEntry.v1_6_1.LogEntry",
            "Created": "2022-10-25T06:51:25-05:00",
            "Description": "Log Entry 374269",
            "EntryType": "Oem",
            "Id": "374269",
            "Links": {
                "OriginOfCondition": {
                    "@odata.id": "/redfish/v1/Managers/iDRAC.Embedded.1"
                }
            },
            "Message": "The session for engineer from 10.193.28.213 using REDFISH is logged off.",
            "MessageArgs": [
                "engineer",
                "10.193.28.213",
                "REDFISH"
            ],
            "MessageArgs@odata.count": 3,
            "MessageId": "USR0032",
            "Name": "Log Entry 374269",
            "Oem": {
                "Dell": {
                    "@odata.type": "#DellLCLogEntry.v1_0_0.DellLCLogEntry",
                    "Category": "Audit",
                    "Comment": null,
                    "LastUpdatedByUser": null
                }
            },
            "OemRecordFormat": "Dell",
            "Severity": "OK"
        },
        {
            "@odata.id": "/redfish/v1/Managers/iDRAC.Embedded.1/LogServices/Lclog/Entries/374268",
            "@odata.type": "#LogEntry.v1_6_1.LogEntry",
            "Created": "2022-10-25T06:51:25-05:00",
            "Description": "Log Entry 374268",
            "EntryType": "Oem",
            "Id": "374268",
            "Links": {
                "OriginOfCondition": {
                    "@odata.id": "/redfish/v1/Managers/iDRAC.Embedded.1"
                }
            },
            "Message": "Successfully logged in using root, from 10.29.152.130 and REDFISH.",
            "MessageArgs": [
                "root",
                "10.29.152.130",
                "REDFISH"
            ],
            "MessageArgs@odata.count": 3,
            "MessageId": "USR0030",
            "Name": "Log Entry 374268",
            "Oem": {
                "Dell": {
                    "@odata.type": "#DellLCLogEntry.v1_0_0.DellLCLogEntry",
                    "Category": "Audit",
                    "Comment": null,
                    "LastUpdatedByUser": null
                }
            },
            "OemRecordFormat": "Dell",
            "Severity": "OK"
        },
        {
            "@odata.id": "/redfish/v1/Managers/iDRAC.Embedded.1/LogServices/Lclog/Entries/374267",
            "@odata.type": "#LogEntry.v1_6_1.LogEntry",
            "Created": "2022-10-25T06:51:24-05:00",
            "Description": "Log Entry 374267",
            "EntryType": "Oem",
            "Id": "374267",
            "Links": {
                "OriginOfCondition": {
                    "@odata.id": "/redfish/v1/Managers/iDRAC.Embedded.1"
                }
            },
            "Message": "The session for root from 10.29.152.130 using REDFISH is logged off.",
            "MessageArgs": [
                "root",
                "10.29.152.130",
                "REDFISH"
            ],
            "MessageArgs@odata.count": 3,
            "MessageId": "USR0032",
            "Name": "Log Entry 374267",
            "Oem": {
                "Dell": {
                    "@odata.type": "#DellLCLogEntry.v1_0_0.DellLCLogEntry",
                    "Category": "Audit",
                    "Comment": null,
                    "LastUpdatedByUser": null
                }
            },
            "OemRecordFormat": "Dell",
            "Severity": "OK"
        },
        {
            "@odata.id": "/redfish/v1/Managers/iDRAC.Embedded.1/LogServices/Lclog/Entries/374266",
            "@odata.type": "#LogEntry.v1_6_1.LogEntry",
            "Created": "2022-10-25T06:48:40-05:00",
            "Description": "Log Entry 374266",
            "EntryType": "Oem",
            "Id": "374266",
            "Links": {
                "OriginOfCondition": {
                    "@odata.id": "/redfish/v1/Managers/iDRAC.Embedded.1"
                }
            },
            "Message": "The session for engineer from 10.106.189.136 using REDFISH is logged off.",
            "MessageArgs": [
                "engineer",
                "10.106.189.136",
                "REDFISH"
            ],
            "MessageArgs@odata.count": 3,
            "MessageId": "USR0032",
            "Name": "Log Entry 374266",
            "Oem": {
                "Dell": {
                    "@odata.type": "#DellLCLogEntry.v1_0_0.DellLCLogEntry",
                    "Category": "Audit",
                    "Comment": null,
                    "LastUpdatedByUser": null
                }
            },
            "OemRecordFormat": "Dell",
            "Severity": "OK"
        },
        {
            "@odata.id": "/redfish/v1/Managers/iDRAC.Embedded.1/LogServices/Lclog/Entries/374265",
            "@odata.type": "#LogEntry.v1_6_1.LogEntry",
            "Created": "2022-10-25T06:48:40-05:00",
            "Description": "Log Entry 374265",
            "EntryType": "Oem",
            "Id": "374265",
            "Links": {},
            "Message": "The previous log entry was repeated 1 times.",
            "MessageArgs": [
                "1"
            ],
            "MessageArgs@odata.count": 1,
            "MessageId": "LOG007",
            "Name": "Log Entry 374265",
            "Oem": {
                "Dell": {
                    "@odata.type": "#DellLCLogEntry.v1_0_0.DellLCLogEntry",
                    "Category": "Audit",
                    "Comment": null,
                    "LastUpdatedByUser": null
                }
            },
            "OemRecordFormat": "Dell",
            "Severity": "OK"
        },
        {
            "@odata.id": "/redfish/v1/Managers/iDRAC.Embedded.1/LogServices/Lclog/Entries/374264",
            "@odata.type": "#LogEntry.v1_6_1.LogEntry",
            "Created": "2022-10-25T06:46:17-05:00",
            "Description": "Log Entry 374264",
            "EntryType": "Oem",
            "Id": "374264",
            "Links": {
                "OriginOfCondition": {
                    "@odata.id": "/redfish/v1/Managers/iDRAC.Embedded.1"
                }
            },
            "Message": "Successfully logged in using engineer, from 10.193.28.213 and REDFISH.",
            "MessageArgs": [
                "engineer",
                "10.193.28.213",
                "REDFISH"
            ],
            "MessageArgs@odata.count": 3,
            "MessageId": "USR0030",
            "Name": "Log Entry 374264",
            "Oem": {
                "Dell": {
                    "@odata.type": "#DellLCLogEntry.v1_0_0.DellLCLogEntry",
                    "Category": "Audit",
                    "Comment": null,
                    "LastUpdatedByUser": null
                }
            },
            "OemRecordFormat": "Dell",
            "Severity": "OK"
        },
        {
            "@odata.id": "/redfish/v1/Managers/iDRAC.Embedded.1/LogServices/Lclog/Entries/374263",
            "@odata.type": "#LogEntry.v1_6_1.LogEntry",
            "Created": "2022-10-25T06:46:17-05:00",
            "Description": "Log Entry 374263",
            "EntryType": "Oem",
            "Id": "374263",
            "Links": {},
            "Message": "The previous log entry was repeated 1 times.",
            "MessageArgs": [
                "1"
            ],
            "MessageArgs@odata.count": 1,
            "MessageId": "LOG007",
            "Name": "Log Entry 374263",
            "Oem": {
                "Dell": {
                    "@odata.type": "#DellLCLogEntry.v1_0_0.DellLCLogEntry",
                    "Category": "Audit",
                    "Comment": null,
                    "LastUpdatedByUser": null
                }
            },
            "OemRecordFormat": "Dell",
            "Severity": "OK"
        },
        {
            "@odata.id": "/redfish/v1/Managers/iDRAC.Embedded.1/LogServices/Lclog/Entries/374262",
            "@odata.type": "#LogEntry.v1_6_1.LogEntry",
            "Created": "2022-10-25T06:46:16-05:00",
            "Description": "Log Entry 374262",
            "EntryType": "Oem",
            "Id": "374262",
            "Links": {
                "OriginOfCondition": {
                    "@odata.id": "/redfish/v1/Managers/iDRAC.Embedded.1"
                }
            },
            "Message": "Successfully logged in using root, from 10.29.152.130 and REDFISH.",
            "MessageArgs": [
                "root",
                "10.29.152.130",
                "REDFISH"
            ],
            "MessageArgs@odata.count": 3,
            "MessageId": "USR0030",
            "Name": "Log Entry 374262",
            "Oem": {
                "Dell": {
                    "@odata.type": "#DellLCLogEntry.v1_0_0.DellLCLogEntry",
                    "Category": "Audit",
                    "Comment": null,
                    "LastUpdatedByUser": null
                }
            },
            "OemRecordFormat": "Dell",
            "Severity": "OK"
        },
        {
            "@odata.id": "/redfish/v1/Managers/iDRAC.Embedded.1/LogServices/Lclog/Entries/374261",
            "@odata.type": "#LogEntry.v1_6_1.LogEntry",
            "Created": "2022-10-25T06:46:16-05:00",
            "Description": "Log Entry 374261",
            "EntryType": "Oem",
            "Id": "374261",
            "Links": {
                "OriginOfCondition": {
                    "@odata.id": "/redfish/v1/Managers/iDRAC.Embedded.1"
                }
            },
            "Message": "The session for engineer from 10.193.28.213 using REDFISH is logged off.",
            "MessageArgs": [
                "engineer",
                "10.193.28.213",
                "REDFISH"
            ],
            "MessageArgs@odata.count": 3,
            "MessageId": "USR0032",
            "Name": "Log Entry 374261",
            "Oem": {
                "Dell": {
                    "@odata.type": "#DellLCLogEntry.v1_0_0.DellLCLogEntry",
                    "Category": "Audit",
                    "Comment": null,
                    "LastUpdatedByUser": null
                }
            },
            "OemRecordFormat": "Dell",
            "Severity": "OK"
        },
        {
            "@odata.id": "/redfish/v1/Managers/iDRAC.Embedded.1/LogServices/Lclog/Entries/374260",
            "@odata.type": "#LogEntry.v1_6_1.LogEntry",
            "Created": "2022-10-25T06:46:16-05:00",
            "Description": "Log Entry 374260",
            "EntryType": "Oem",
            "Id": "374260",
            "Links": {
                "OriginOfCondition": {
                    "@odata.id": "/redfish/v1/Managers/iDRAC.Embedded.1"
                }
            },
            "Message": "The session for root from 10.29.152.130 using REDFISH is logged off.",
            "MessageArgs": [
                "root",
                "10.29.152.130",
                "REDFISH"
            ],
            "MessageArgs@odata.count": 3,
            "MessageId": "USR0032",
            "Name": "Log Entry 374260",
            "Oem": {
                "Dell": {
                    "@odata.type": "#DellLCLogEntry.v1_0_0.DellLCLogEntry",
                    "Category": "Audit",
                    "Comment": null,
                    "LastUpdatedByUser": null
                }
            },
            "OemRecordFormat": "Dell",
            "Severity": "OK"
        },
        {
            "@odata.id": "/redfish/v1/Managers/iDRAC.Embedded.1/LogServices/Lclog/Entries/374259",
            "@odata.type": "#LogEntry.v1_6_1.LogEntry",
            "Created": "2022-10-25T06:46:16-05:00",
            "Description": "Log Entry 374259",
            "EntryType": "Oem",
            "Id": "374259",
            "Links": {},
            "Message": "The previous log entry was repeated 1 times.",
            "MessageArgs": [
                "1"
            ],
            "MessageArgs@odata.count": 1,
            "MessageId": "LOG007",
            "Name": "Log Entry 374259",
            "Oem": {
                "Dell": {
                    "@odata.type": "#DellLCLogEntry.v1_0_0.DellLCLogEntry",
                    "Category": "Audit",
                    "Comment": null,
                    "LastUpdatedByUser": null
                }
            },
            "OemRecordFormat": "Dell",
            "Severity": "OK"
        },
        {
            "@odata.id": "/redfish/v1/Managers/iDRAC.Embedded.1/LogServices/Lclog/Entries/374258",
            "@odata.type": "#LogEntry.v1_6_1.LogEntry",
            "Created": "2022-10-25T06:43:36-05:00",
            "Description": "Log Entry 374258",
            "EntryType": "Oem",
            "Id": "374258",
            "Links": {
                "OriginOfCondition": {
                    "@odata.id": "/redfish/v1/Managers/iDRAC.Embedded.1"
                }
            },
            "Message": "Successfully logged in using engineer, from 10.106.189.136 and REDFISH.",
            "MessageArgs": [
                "engineer",
                "10.106.189.136",
                "REDFISH"
            ],
            "MessageArgs@odata.count": 3,
            "MessageId": "USR0030",
            "Name": "Log Entry 374258",
            "Oem": {
                "Dell": {
                    "@odata.type": "#DellLCLogEntry.v1_0_0.DellLCLogEntry",
                    "Category": "Audit",
                    "Comment": null,
                    "LastUpdatedByUser": null
                }
            },
            "OemRecordFormat": "Dell",
            "Severity": "OK"
        },
        {
            "@odata.id": "/redfish/v1/Managers/iDRAC.Embedded.1/LogServices/Lclog/Entries/374257",
            "@odata.type": "#LogEntry.v1_6_1.LogEntry",
            "Created": "2022-10-25T06:43:19-05:00",
            "Description": "Log Entry 374257",
            "EntryType": "Oem",
            "Id": "374257",
            "Links": {
                "OriginOfCondition": {
                    "@odata.id": "/redfish/v1/Managers/iDRAC.Embedded.1"
                }
            },
            "Message": "Successfully logged in using complab, from 10.29.153.91 and REDFISH.",
            "MessageArgs": [
                "complab",
                "10.29.153.91",
                "REDFISH"
            ],
            "MessageArgs@odata.count": 3,
            "MessageId": "USR0030",
            "Name": "Log Entry 374257",
            "Oem": {
                "Dell": {
                    "@odata.type": "#DellLCLogEntry.v1_0_0.DellLCLogEntry",
                    "Category": "Audit",
                    "Comment": null,
                    "LastUpdatedByUser": null
                }
            },
            "OemRecordFormat": "Dell",
            "Severity": "OK"
        },
        {
            "@odata.id": "/redfish/v1/Managers/iDRAC.Embedded.1/LogServices/Lclog/Entries/374256",
            "@odata.type": "#LogEntry.v1_6_1.LogEntry",
            "Created": "2022-10-25T06:43:19-05:00",
            "Description": "Log Entry 374256",
            "EntryType": "Oem",
            "Id": "374256",
            "Links": {
                "OriginOfCondition": {
                    "@odata.id": "/redfish/v1/Managers/iDRAC.Embedded.1"
                }
            },
            "Message": "Successfully logged in using complab, from 10.29.153.90 and REDFISH.",
            "MessageArgs": [
                "complab",
                "10.29.153.90",
                "REDFISH"
            ],
            "MessageArgs@odata.count": 3,
            "MessageId": "USR0030",
            "Name": "Log Entry 374256",
            "Oem": {
                "Dell": {
                    "@odata.type": "#DellLCLogEntry.v1_0_0.DellLCLogEntry",
                    "Category": "Audit",
                    "Comment": null,
                    "LastUpdatedByUser": null
                }
            },
            "OemRecordFormat": "Dell",
            "Severity": "OK"
        },
        {
            "@odata.id": "/redfish/v1/Managers/iDRAC.Embedded.1/LogServices/Lclog/Entries/374255",
            "@odata.type": "#LogEntry.v1_6_1.LogEntry",
            "Created": "2022-10-25T06:43:19-05:00",
            "Description": "Log Entry 374255",
            "EntryType": "Oem",
            "Id": "374255",
            "Links": {},
            "Message": "The previous log entry was repeated 1 times.",
            "MessageArgs": [
                "1"
            ],
            "MessageArgs@odata.count": 1,
            "MessageId": "LOG007",
            "Name": "Log Entry 374255",
            "Oem": {
                "Dell": {
                    "@odata.type": "#DellLCLogEntry.v1_0_0.DellLCLogEntry",
                    "Category": "Audit",
                    "Comment": null,
                    "LastUpdatedByUser": null
                }
            },
            "OemRecordFormat": "Dell",
            "Severity": "OK"
        },
        {
            "@odata.id": "/redfish/v1/Managers/iDRAC.Embedded.1/LogServices/Lclog/Entries/374254",
            "@odata.type": "#LogEntry.v1_6_1.LogEntry",
            "Created": "2022-10-25T06:41:09-05:00",
            "Description": "Log Entry 374254",
            "EntryType": "Oem",
            "Id": "374254",
            "Links": {
                "OriginOfCondition": {
                    "@odata.id": "/redfish/v1/Managers/iDRAC.Embedded.1"
                }
            },
            "Message": "Successfully logged in using root, from 10.29.152.130 and REDFISH.",
            "MessageArgs": [
                "root",
                "10.29.152.130",
                "REDFISH"
            ],
            "MessageArgs@odata.count": 3,
            "MessageId": "USR0030",
            "Name": "Log Entry 374254",
            "Oem": {
                "Dell": {
                    "@odata.type": "#DellLCLogEntry.v1_0_0.DellLCLogEntry",
                    "Category": "Audit",
                    "Comment": null,
                    "LastUpdatedByUser": null
                }
            },
            "OemRecordFormat": "Dell",
            "Severity": "OK"
        },
        {
            "@odata.id": "/redfish/v1/Managers/iDRAC.Embedded.1/LogServices/Lclog/Entries/374253",
            "@odata.type": "#LogEntry.v1_6_1.LogEntry",
            "Created": "2022-10-25T06:41:09-05:00",
            "Description": "Log Entry 374253",
            "EntryType": "Oem",
            "Id": "374253",
            "Links": {},
            "Message": "The previous log entry was repeated 1 times.",
            "MessageArgs": [
                "1"
            ],
            "MessageArgs@odata.count": 1,
            "MessageId": "LOG007",
            "Name": "Log Entry 374253",
            "Oem": {
                "Dell": {
                    "@odata.type": "#DellLCLogEntry.v1_0_0.DellLCLogEntry",
                    "Category": "Audit",
                    "Comment": null,
                    "LastUpdatedByUser": null
                }
            },
            "OemRecordFormat": "Dell",
            "Severity": "OK"
        },
        {
            "@odata.id": "/redfish/v1/Managers/iDRAC.Embedded.1/LogServices/Lclog/Entries/374252",
            "@odata.type": "#LogEntry.v1_6_1.LogEntry",
            "Created": "2022-10-25T06:41:09-05:00",
            "Description": "Log Entry 374252",
            "EntryType": "Oem",
            "Id": "374252",
            "Links": {
                "OriginOfCondition": {
                    "@odata.id": "/redfish/v1/Managers/iDRAC.Embedded.1"
                }
            },
            "Message": "Successfully logged in using engineer, from 10.193.28.213 and REDFISH.",
            "MessageArgs": [
                "engineer",
                "10.193.28.213",
                "REDFISH"
            ],
            "MessageArgs@odata.count": 3,
            "MessageId": "USR0030",
            "Name": "Log Entry 374252",
            "Oem": {
                "Dell": {
                    "@odata.type": "#DellLCLogEntry.v1_0_0.DellLCLogEntry",
                    "Category": "Audit",
                    "Comment": null,
                    "LastUpdatedByUser": null
                }
            },
            "OemRecordFormat": "Dell",
            "Severity": "OK"
        },
        {
            "@odata.id": "/redfish/v1/Managers/iDRAC.Embedded.1/LogServices/Lclog/Entries/374251",
            "@odata.type": "#LogEntry.v1_6_1.LogEntry",
            "Created": "2022-10-25T06:41:09-05:00",
            "Description": "Log Entry 374251",
            "EntryType": "Oem",
            "Id": "374251",
            "Links": {
                "OriginOfCondition": {
                    "@odata.id": "/redfish/v1/Managers/iDRAC.Embedded.1"
                }
            },
            "Message": "The session for root from 10.29.152.130 using REDFISH is logged off.",
            "MessageArgs": [
                "root",
                "10.29.152.130",
                "REDFISH"
            ],
            "MessageArgs@odata.count": 3,
            "MessageId": "USR0032",
            "Name": "Log Entry 374251",
            "Oem": {
                "Dell": {
                    "@odata.type": "#DellLCLogEntry.v1_0_0.DellLCLogEntry",
                    "Category": "Audit",
                    "Comment": null,
                    "LastUpdatedByUser": null
                }
            },
            "OemRecordFormat": "Dell",
            "Severity": "OK"
        },
        {
            "@odata.id": "/redfish/v1/Managers/iDRAC.Embedded.1/LogServices/Lclog/Entries/374250",
            "@odata.type": "#LogEntry.v1_6_1.LogEntry",
            "Created": "2022-10-25T06:41:08-05:00",
            "Description": "Log Entry 374250",
            "EntryType": "Oem",
            "Id": "374250",
            "Links": {
                "OriginOfCondition": {
                    "@odata.id": "/redfish/v1/Managers/iDRAC.Embedded.1"
                }
            },
            "Message": "The session for engineer from 10.193.28.213 using REDFISH is logged off.",
            "MessageArgs": [
                "engineer",
                "10.193.28.213",
                "REDFISH"
            ],
            "MessageArgs@odata.count": 3,
            "MessageId": "USR0032",
            "Name": "Log Entry 374250",
            "Oem": {
                "Dell": {
                    "@odata.type": "#DellLCLogEntry.v1_0_0.DellLCLogEntry",
                    "Category": "Audit",
                    "Comment": null,
                    "LastUpdatedByUser": null
                }
            },
            "OemRecordFormat": "Dell",
            "Severity": "OK"
        },
        {
            "@odata.id": "/redfish/v1/Managers/iDRAC.Embedded.1/LogServices/Lclog/Entries/374249",
            "@odata.type": "#LogEntry.v1_6_1.LogEntry",
            "Created": "2022-10-25T06:41:08-05:00",
            "Description": "Log Entry 374249",
            "EntryType": "Oem",
            "Id": "374249",
            "Links": {},
            "Message": "The previous log entry was repeated 1 times.",
            "MessageArgs": [
                "1"
            ],
            "MessageArgs@odata.count": 1,
            "MessageId": "LOG007",
            "Name": "Log Entry 374249",
            "Oem": {
                "Dell": {
                    "@odata.type": "#DellLCLogEntry.v1_0_0.DellLCLogEntry",
                    "Category": "Audit",
                    "Comment": null,
                    "LastUpdatedByUser": null
                }
            },
            "OemRecordFormat": "Dell",
            "Severity": "OK"
        },
        {
            "@odata.id": "/redfish/v1/Managers/iDRAC.Embedded.1/LogServices/Lclog/Entries/374248",
            "@odata.type": "#LogEntry.v1_6_1.LogEntry",
            "Created": "2022-10-25T06:36:01-05:00",
            "Description": "Log Entry 374248",
            "EntryType": "Oem",
            "Id": "374248",
            "Links": {
                "OriginOfCondition": {
                    "@odata.id": "/redfish/v1/Managers/iDRAC.Embedded.1"
                }
            },
            "Message": "Successfully logged in using engineer, from 10.193.28.213 and REDFISH.",
            "MessageArgs": [
                "engineer",
                "10.193.28.213",
                "REDFISH"
            ],
            "MessageArgs@odata.count": 3,
            "MessageId": "USR0030",
            "Name": "Log Entry 374248",
            "Oem": {
                "Dell": {
                    "@odata.type": "#DellLCLogEntry.v1_0_0.DellLCLogEntry",
                    "Category": "Audit",
                    "Comment": null,
                    "LastUpdatedByUser": null
                }
            },
            "OemRecordFormat": "Dell",
            "Severity": "OK"
        },
        {
            "@odata.id": "/redfish/v1/Managers/iDRAC.Embedded.1/LogServices/Lclog/Entries/374247",
            "@odata.type": "#LogEntry.v1_6_1.LogEntry",
            "Created": "2022-10-25T06:36:01-05:00",
            "Description": "Log Entry 374247",
            "EntryType": "Oem",
            "Id": "374247",
            "Links": {},
            "Message": "The previous log entry was repeated 1 times.",
            "MessageArgs": [
                "1"
            ],
            "MessageArgs@odata.count": 1,
            "MessageId": "LOG007",
            "Name": "Log Entry 374247",
            "Oem": {
                "Dell": {
                    "@odata.type": "#DellLCLogEntry.v1_0_0.DellLCLogEntry",
                    "Category": "Audit",
                    "Comment": null,
                    "LastUpdatedByUser": null
                }
            },
            "OemRecordFormat": "Dell",
            "Severity": "OK"
        },
        {
            "@odata.id": "/redfish/v1/Managers/iDRAC.Embedded.1/LogServices/Lclog/Entries/374246",
            "@odata.type": "#LogEntry.v1_6_1.LogEntry",
            "Created": "2022-10-25T06:36:01-05:00",
            "Description": "Log Entry 374246",
            "EntryType": "Oem",
            "Id": "374246",
            "Links": {
                "OriginOfCondition": {
                    "@odata.id": "/redfish/v1/Managers/iDRAC.Embedded.1"
                }
            },
            "Message": "Successfully logged in using root, from 10.29.152.130 and REDFISH.",
            "MessageArgs": [
                "root",
                "10.29.152.130",
                "REDFISH"
            ],
            "MessageArgs@odata.count": 3,
            "MessageId": "USR0030",
            "Name": "Log Entry 374246",
            "Oem": {
                "Dell": {
                    "@odata.type": "#DellLCLogEntry.v1_0_0.DellLCLogEntry",
                    "Category": "Audit",
                    "Comment": null,
                    "LastUpdatedByUser": null
                }
            },
            "OemRecordFormat": "Dell",
            "Severity": "OK"
        },
        {
            "@odata.id": "/redfish/v1/Managers/iDRAC.Embedded.1/LogServices/Lclog/Entries/374245",
            "@odata.type": "#LogEntry.v1_6_1.LogEntry",
            "Created": "2022-10-25T06:36:00-05:00",
            "Description": "Log Entry 374245",
            "EntryType": "Oem",
            "Id": "374245",
            "Links": {
                "OriginOfCondition": {
                    "@odata.id": "/redfish/v1/Managers/iDRAC.Embedded.1"
                }
            },
            "Message": "The session for root from 10.29.152.130 using REDFISH is logged off.",
            "MessageArgs": [
                "root",
                "10.29.152.130",
                "REDFISH"
            ],
            "MessageArgs@odata.count": 3,
            "MessageId": "USR0032",
            "Name": "Log Entry 374245",
            "Oem": {
                "Dell": {
                    "@odata.type": "#DellLCLogEntry.v1_0_0.DellLCLogEntry",
                    "Category": "Audit",
                    "Comment": null,
                    "LastUpdatedByUser": null
                }
            },
            "OemRecordFormat": "Dell",
            "Severity": "OK"
        },
        {
            "@odata.id": "/redfish/v1/Managers/iDRAC.Embedded.1/LogServices/Lclog/Entries/374244",
            "@odata.type": "#LogEntry.v1_6_1.LogEntry",
            "Created": "2022-10-25T06:36:00-05:00",
            "Description": "Log Entry 374244",
            "EntryType": "Oem",
            "Id": "374244",
            "Links": {
                "OriginOfCondition": {
                    "@odata.id": "/redfish/v1/Managers/iDRAC.Embedded.1"
                }
            },
            "Message": "The session for engineer from 10.193.28.213 using REDFISH is logged off.",
            "MessageArgs": [
                "engineer",
                "10.193.28.213",
                "REDFISH"
            ],
            "MessageArgs@odata.count": 3,
            "MessageId": "USR0032",
            "Name": "Log Entry 374244",
            "Oem": {
                "Dell": {
                    "@odata.type": "#DellLCLogEntry.v1_0_0.DellLCLogEntry",
                    "Category": "Audit",
                    "Comment": null,
                    "LastUpdatedByUser": null
                }
            },
            "OemRecordFormat": "Dell",
            "Severity": "OK"
        },
        {
            "@odata.id": "/redfish/v1/Managers/iDRAC.Embedded.1/LogServices/Lclog/Entries/374243",
            "@odata.type": "#LogEntry.v1_6_1.LogEntry",
            "Created": "2022-10-25T06:33:39-05:00",
            "Description": "Log Entry 374243",
            "EntryType": "Oem",
            "Id": "374243",
            "Links": {
                "OriginOfCondition": {
                    "@odata.id": "/redfish/v1/Managers/iDRAC.Embedded.1"
                }
            },
            "Message": "The session for engineer from 10.106.189.136 using REDFISH is logged off.",
            "MessageArgs": [
                "engineer",
                "10.106.189.136",
                "REDFISH"
            ],
            "MessageArgs@odata.count": 3,
            "MessageId": "USR0032",
            "Name": "Log Entry 374243",
            "Oem": {
                "Dell": {
                    "@odata.type": "#DellLCLogEntry.v1_0_0.DellLCLogEntry",
                    "Category": "Audit",
                    "Comment": null,
                    "LastUpdatedByUser": null
                }
            },
            "OemRecordFormat": "Dell",
            "Severity": "OK"
        },
        {
            "@odata.id": "/redfish/v1/Managers/iDRAC.Embedded.1/LogServices/Lclog/Entries/374242",
            "@odata.type": "#LogEntry.v1_6_1.LogEntry",
            "Created": "2022-10-25T06:33:39-05:00",
            "Description": "Log Entry 374242",
            "EntryType": "Oem",
            "Id": "374242",
            "Links": {},
            "Message": "The previous log entry was repeated 1 times.",
            "MessageArgs": [
                "1"
            ],
            "MessageArgs@odata.count": 1,
            "MessageId": "LOG007",
            "Name": "Log Entry 374242",
            "Oem": {
                "Dell": {
                    "@odata.type": "#DellLCLogEntry.v1_0_0.DellLCLogEntry",
                    "Category": "Audit",
                    "Comment": null,
                    "LastUpdatedByUser": null
                }
            },
            "OemRecordFormat": "Dell",
            "Severity": "OK"
        },
        {
            "@odata.id": "/redfish/v1/Managers/iDRAC.Embedded.1/LogServices/Lclog/Entries/374241",
            "@odata.type": "#LogEntry.v1_6_1.LogEntry",
            "Created": "2022-10-25T06:30:53-05:00",
            "Description": "Log Entry 374241",
            "EntryType": "Oem",
            "Id": "374241",
            "Links": {
                "OriginOfCondition": {
                    "@odata.id": "/redfish/v1/Managers/iDRAC.Embedded.1"
                }
            },
            "Message": "Successfully logged in using root, from 10.29.152.130 and REDFISH.",
            "MessageArgs": [
                "root",
                "10.29.152.130",
                "REDFISH"
            ],
            "MessageArgs@odata.count": 3,
            "MessageId": "USR0030",
            "Name": "Log Entry 374241",
            "Oem": {
                "Dell": {
                    "@odata.type": "#DellLCLogEntry.v1_0_0.DellLCLogEntry",
                    "Category": "Audit",
                    "Comment": null,
                    "LastUpdatedByUser": null
                }
            },
            "OemRecordFormat": "Dell",
            "Severity": "OK"
        },
        {
            "@odata.id": "/redfish/v1/Managers/iDRAC.Embedded.1/LogServices/Lclog/Entries/374240",
            "@odata.type": "#LogEntry.v1_6_1.LogEntry",
            "Created": "2022-10-25T06:30:53-05:00",
            "Description": "Log Entry 374240",
            "EntryType": "Oem",
            "Id": "374240",
            "Links": {},
            "Message": "The previous log entry was repeated 1 times.",
            "MessageArgs": [
                "1"
            ],
            "MessageArgs@odata.count": 1,
            "MessageId": "LOG007",
            "Name": "Log Entry 374240",
            "Oem": {
                "Dell": {
                    "@odata.type": "#DellLCLogEntry.v1_0_0.DellLCLogEntry",
                    "Category": "Audit",
                    "Comment": null,
                    "LastUpdatedByUser": null
                }
            },
            "OemRecordFormat": "Dell",
            "Severity": "OK"
        },
        {
            "@odata.id": "/redfish/v1/Managers/iDRAC.Embedded.1/LogServices/Lclog/Entries/374239",
            "@odata.type": "#LogEntry.v1_6_1.LogEntry",
            "Created": "2022-10-25T06:30:52-05:00",
            "Description": "Log Entry 374239",
            "EntryType": "Oem",
            "Id": "374239",
            "Links": {
                "OriginOfCondition": {
                    "@odata.id": "/redfish/v1/Managers/iDRAC.Embedded.1"
                }
            },
            "Message": "Successfully logged in using engineer, from 10.193.28.213 and REDFISH.",
            "MessageArgs": [
                "engineer",
                "10.193.28.213",
                "REDFISH"
            ],
            "MessageArgs@odata.count": 3,
            "MessageId": "USR0030",
            "Name": "Log Entry 374239",
            "Oem": {
                "Dell": {
                    "@odata.type": "#DellLCLogEntry.v1_0_0.DellLCLogEntry",
                    "Category": "Audit",
                    "Comment": null,
                    "LastUpdatedByUser": null
                }
            },
            "OemRecordFormat": "Dell",
            "Severity": "OK"
        },
        {
            "@odata.id": "/redfish/v1/Managers/iDRAC.Embedded.1/LogServices/Lclog/Entries/374238",
            "@odata.type": "#LogEntry.v1_6_1.LogEntry",
            "Created": "2022-10-25T06:30:52-05:00",
            "Description": "Log Entry 374238",
            "EntryType": "Oem",
            "Id": "374238",
            "Links": {
                "OriginOfCondition": {
                    "@odata.id": "/redfish/v1/Managers/iDRAC.Embedded.1"
                }
            },
            "Message": "The session for root from 10.29.152.130 using REDFISH is logged off.",
            "MessageArgs": [
                "root",
                "10.29.152.130",
                "REDFISH"
            ],
            "MessageArgs@odata.count": 3,
            "MessageId": "USR0032",
            "Name": "Log Entry 374238",
            "Oem": {
                "Dell": {
                    "@odata.type": "#DellLCLogEntry.v1_0_0.DellLCLogEntry",
                    "Category": "Audit",
                    "Comment": null,
                    "LastUpdatedByUser": null
                }
            },
            "OemRecordFormat": "Dell",
            "Severity": "OK"
        },
        {
            "@odata.id": "/redfish/v1/Managers/iDRAC.Embedded.1/LogServices/Lclog/Entries/374237",
            "@odata.type": "#LogEntry.v1_6_1.LogEntry",
            "Created": "2022-10-25T06:30:52-05:00",
            "Description": "Log Entry 374237",
            "EntryType": "Oem",
            "Id": "374237",
            "Links": {
                "OriginOfCondition": {
                    "@odata.id": "/redfish/v1/Managers/iDRAC.Embedded.1"
                }
            },
            "Message": "The session for engineer from 10.193.28.213 using REDFISH is logged off.",
            "MessageArgs": [
                "engineer",
                "10.193.28.213",
                "REDFISH"
            ],
            "MessageArgs@odata.count": 3,
            "MessageId": "USR0032",
            "Name": "Log Entry 374237",
            "Oem": {
                "Dell": {
                    "@odata.type": "#DellLCLogEntry.v1_0_0.DellLCLogEntry",
                    "Category": "Audit",
                    "Comment": null,
                    "LastUpdatedByUser": null
                }
            },
            "OemRecordFormat": "Dell",
            "Severity": "OK"
        },
        {
            "@odata.id": "/redfish/v1/Managers/iDRAC.Embedded.1/LogServices/Lclog/Entries/374236",
            "@odata.type": "#LogEntry.v1_6_1.LogEntry",
            "Created": "2022-10-25T06:30:52-05:00",
            "Description": "Log Entry 374236",
            "EntryType": "Oem",
            "Id": "374236",
            "Links": {},
            "Message": "The previous log entry was repeated 1 times.",
            "MessageArgs": [
                "1"
            ],
            "MessageArgs@odata.count": 1,
            "MessageId": "LOG007",
            "Name": "Log Entry 374236",
            "Oem": {
                "Dell": {
                    "@odata.type": "#DellLCLogEntry.v1_0_0.DellLCLogEntry",
                    "Category": "Audit",
                    "Comment": null,
                    "LastUpdatedByUser": null
                }
            },
            "OemRecordFormat": "Dell",
            "Severity": "OK"
        },
        {
            "@odata.id": "/redfish/v1/Managers/iDRAC.Embedded.1/LogServices/Lclog/Entries/374235",
            "@odata.type": "#LogEntry.v1_6_1.LogEntry",
            "Created": "2022-10-25T06:28:36-05:00",
            "Description": "Log Entry 374235",
            "EntryType": "Oem",
            "Id": "374235",
            "Links": {
                "OriginOfCondition": {
                    "@odata.id": "/redfish/v1/Managers/iDRAC.Embedded.1"
                }
            },
            "Message": "Successfully logged in using engineer, from 10.106.189.136 and REDFISH.",
            "MessageArgs": [
                "engineer",
                "10.106.189.136",
                "REDFISH"
            ],
            "MessageArgs@odata.count": 3,
            "MessageId": "USR0030",
            "Name": "Log Entry 374235",
            "Oem": {
                "Dell": {
                    "@odata.type": "#DellLCLogEntry.v1_0_0.DellLCLogEntry",
                    "Category": "Audit",
                    "Comment": null,
                    "LastUpdatedByUser": null
                }
            },
            "OemRecordFormat": "Dell",
            "Severity": "OK"
        },
        {
            "@odata.id": "/redfish/v1/Managers/iDRAC.Embedded.1/LogServices/Lclog/Entries/374234",
            "@odata.type": "#LogEntry.v1_6_1.LogEntry",
            "Created": "2022-10-25T06:28:19-05:00",
            "Description": "Log Entry 374234",
            "EntryType": "Oem",
            "Id": "374234",
            "Links": {
                "OriginOfCondition": {
                    "@odata.id": "/redfish/v1/Managers/iDRAC.Embedded.1"
                }
            },
            "Message": "Successfully logged in using complab, from 10.29.153.90 and REDFISH.",
            "MessageArgs": [
                "complab",
                "10.29.153.90",
                "REDFISH"
            ],
            "MessageArgs@odata.count": 3,
            "MessageId": "USR0030",
            "Name": "Log Entry 374234",
            "Oem": {
                "Dell": {
                    "@odata.type": "#DellLCLogEntry.v1_0_0.DellLCLogEntry",
                    "Category": "Audit",
                    "Comment": null,
                    "LastUpdatedByUser": null
                }
            },
            "OemRecordFormat": "Dell",
            "Severity": "OK"
        },
        {
            "@odata.id": "/redfish/v1/Managers/iDRAC.Embedded.1/LogServices/Lclog/Entries/374233",
            "@odata.type": "#LogEntry.v1_6_1.LogEntry",
            "Created": "2022-10-25T06:28:19-05:00",
            "Description": "Log Entry 374233",
            "EntryType": "Oem",
            "Id": "374233",
            "Links": {
                "OriginOfCondition": {
                    "@odata.id": "/redfish/v1/Managers/iDRAC.Embedded.1"
                }
            },
            "Message": "Successfully logged in using complab, from 10.29.153.91 and REDFISH.",
            "MessageArgs": [
                "complab",
                "10.29.153.91",
                "REDFISH"
            ],
            "MessageArgs@odata.count": 3,
            "MessageId": "USR0030",
            "Name": "Log Entry 374233",
            "Oem": {
                "Dell": {
                    "@odata.type": "#DellLCLogEntry.v1_0_0.DellLCLogEntry",
                    "Category": "Audit",
                    "Comment": null,
                    "LastUpdatedByUser": null
                }
            },
            "OemRecordFormat": "Dell",
            "Severity": "OK"
        },
        {
            "@odata.id": "/redfish/v1/Managers/iDRAC.Embedded.1/LogServices/Lclog/Entries/374232",
            "@odata.type": "#LogEntry.v1_6_1.LogEntry",
            "Created": "2022-10-25T06:27:26-05:00",
            "Description": "Log Entry 374232",
            "EntryType": "Oem",
            "Id": "374232",
            "Links": {
                "OriginOfCondition": {
                    "@odata.id": "/redfish/v1/Managers/iDRAC.Embedded.1"
                }
            },
            "Message": "The session for engineer from 10.106.189.136 using REDFISH is logged off.",
            "MessageArgs": [
                "engineer",
                "10.106.189.136",
                "REDFISH"
            ],
            "MessageArgs@odata.count": 3,
            "MessageId": "USR0032",
            "Name": "Log Entry 374232",
            "Oem": {
                "Dell": {
                    "@odata.type": "#DellLCLogEntry.v1_0_0.DellLCLogEntry",
                    "Category": "Audit",
                    "Comment": null,
                    "LastUpdatedByUser": null
                }
            },
            "OemRecordFormat": "Dell",
            "Severity": "OK"
        },
        {
            "@odata.id": "/redfish/v1/Managers/iDRAC.Embedded.1/LogServices/Lclog/Entries/374231",
            "@odata.type": "#LogEntry.v1_6_1.LogEntry",
            "Created": "2022-10-25T06:27:26-05:00",
            "Description": "Log Entry 374231",
            "EntryType": "Oem",
            "Id": "374231",
            "Links": {},
            "Message": "The previous log entry was repeated 1 times.",
            "MessageArgs": [
                "1"
            ],
            "MessageArgs@odata.count": 1,
            "MessageId": "LOG007",
            "Name": "Log Entry 374231",
            "Oem": {
                "Dell": {
                    "@odata.type": "#DellLCLogEntry.v1_0_0.DellLCLogEntry",
                    "Category": "Audit",
                    "Comment": null,
                    "LastUpdatedByUser": null
                }
            },
            "OemRecordFormat": "Dell",
            "Severity": "OK"
        },
        {
            "@odata.id": "/redfish/v1/Managers/iDRAC.Embedded.1/LogServices/Lclog/Entries/374230",
            "@odata.type": "#LogEntry.v1_6_1.LogEntry",
            "Created": "2022-10-25T06:25:45-05:00",
            "Description": "Log Entry 374230",
            "EntryType": "Oem",
            "Id": "374230",
            "Links": {
                "OriginOfCondition": {
                    "@odata.id": "/redfish/v1/Managers/iDRAC.Embedded.1"
                }
            },
            "Message": "Successfully logged in using engineer, from 10.193.28.213 and REDFISH.",
            "MessageArgs": [
                "engineer",
                "10.193.28.213",
                "REDFISH"
            ],
            "MessageArgs@odata.count": 3,
            "MessageId": "USR0030",
            "Name": "Log Entry 374230",
            "Oem": {
                "Dell": {
                    "@odata.type": "#DellLCLogEntry.v1_0_0.DellLCLogEntry",
                    "Category": "Audit",
                    "Comment": null,
                    "LastUpdatedByUser": null
                }
            },
            "OemRecordFormat": "Dell",
            "Severity": "OK"
        },
        {
            "@odata.id": "/redfish/v1/Managers/iDRAC.Embedded.1/LogServices/Lclog/Entries/374229",
            "@odata.type": "#LogEntry.v1_6_1.LogEntry",
            "Created": "2022-10-25T06:25:45-05:00",
            "Description": "Log Entry 374229",
            "EntryType": "Oem",
            "Id": "374229",
            "Links": {},
            "Message": "The previous log entry was repeated 1 times.",
            "MessageArgs": [
                "1"
            ],
            "MessageArgs@odata.count": 1,
            "MessageId": "LOG007",
            "Name": "Log Entry 374229",
            "Oem": {
                "Dell": {
                    "@odata.type": "#DellLCLogEntry.v1_0_0.DellLCLogEntry",
                    "Category": "Audit",
                    "Comment": null,
                    "LastUpdatedByUser": null
                }
            },
            "OemRecordFormat": "Dell",
            "Severity": "OK"
        },
        {
            "@odata.id": "/redfish/v1/Managers/iDRAC.Embedded.1/LogServices/Lclog/Entries/374228",
            "@odata.type": "#LogEntry.v1_6_1.LogEntry",
            "Created": "2022-10-25T06:25:45-05:00",
            "Description": "Log Entry 374228",
            "EntryType": "Oem",
            "Id": "374228",
            "Links": {
                "OriginOfCondition": {
                    "@odata.id": "/redfish/v1/Managers/iDRAC.Embedded.1"
                }
            },
            "Message": "Successfully logged in using root, from 10.29.152.130 and REDFISH.",
            "MessageArgs": [
                "root",
                "10.29.152.130",
                "REDFISH"
            ],
            "MessageArgs@odata.count": 3,
            "MessageId": "USR0030",
            "Name": "Log Entry 374228",
            "Oem": {
                "Dell": {
                    "@odata.type": "#DellLCLogEntry.v1_0_0.DellLCLogEntry",
                    "Category": "Audit",
                    "Comment": null,
                    "LastUpdatedByUser": null
                }
            },
            "OemRecordFormat": "Dell",
            "Severity": "OK"
        },
        {
            "@odata.id": "/redfish/v1/Managers/iDRAC.Embedded.1/LogServices/Lclog/Entries/374227",
            "@odata.type": "#LogEntry.v1_6_1.LogEntry",
            "Created": "2022-10-25T06:25:44-05:00",
            "Description": "Log Entry 374227",
            "EntryType": "Oem",
            "Id": "374227",
            "Links": {
                "OriginOfCondition": {
                    "@odata.id": "/redfish/v1/Managers/iDRAC.Embedded.1"
                }
            },
            "Message": "The session for root from 10.29.152.130 using REDFISH is logged off.",
            "MessageArgs": [
                "root",
                "10.29.152.130",
                "REDFISH"
            ],
            "MessageArgs@odata.count": 3,
            "MessageId": "USR0032",
            "Name": "Log Entry 374227",
            "Oem": {
                "Dell": {
                    "@odata.type": "#DellLCLogEntry.v1_0_0.DellLCLogEntry",
                    "Category": "Audit",
                    "Comment": null,
                    "LastUpdatedByUser": null
                }
            },
            "OemRecordFormat": "Dell",
            "Severity": "OK"
        },
        {
            "@odata.id": "/redfish/v1/Managers/iDRAC.Embedded.1/LogServices/Lclog/Entries/374226",
            "@odata.type": "#LogEntry.v1_6_1.LogEntry",
            "Created": "2022-10-25T06:25:44-05:00",
            "Description": "Log Entry 374226",
            "EntryType": "Oem",
            "Id": "374226",
            "Links": {
                "OriginOfCondition": {
                    "@odata.id": "/redfish/v1/Managers/iDRAC.Embedded.1"
                }
            },
            "Message": "The session for engineer from 10.193.28.213 using REDFISH is logged off.",
            "MessageArgs": [
                "engineer",
                "10.193.28.213",
                "REDFISH"
            ],
            "MessageArgs@odata.count": 3,
            "MessageId": "USR0032",
            "Name": "Log Entry 374226",
            "Oem": {
                "Dell": {
                    "@odata.type": "#DellLCLogEntry.v1_0_0.DellLCLogEntry",
                    "Category": "Audit",
                    "Comment": null,
                    "LastUpdatedByUser": null
                }
            },
            "OemRecordFormat": "Dell",
            "Severity": "OK"
        }
    ],
    "Members@odata.count": 4413,
    "Members@odata.nextLink": "/redfish/v1/Managers/iDRAC.Embedded.1/LogServices/Lclog/Entries?$skip=3600",
    "Name": "Log Entry Collection"
}