{
    "@odata.context": "/redfish/v1/$metadata#HpeESKM.HpeESKM",
    "@odata.etag": "W/\"075B3A10\"",
    "@odata.id": "/redfish/v1/Managers/1/SecurityService/ESKM",
    "@odata.type": "#HpeESKM.v2_0_0.HpeESKM",
    "Id": "ESKM",
    "Actions": {
        "#HpeESKM.ClearESKMLog": {
            "target": "/redfish/v1/Managers/1/SecurityService/ESKM/Actions/HpeESKM.ClearESKMLog"
        },
        "#HpeESKM.TestESKMConnections": {
            "target": "/redfish/v1/Managers/1/SecurityService/ESKM/Actions/HpeESKM.TestESKMConnections"
        }
    },
    "KeyManagerConfig": {
        "AccountGroup": "",
        "AccountName": "ilo-b47af1bd4c94",
        "ESKMLocalCACertificateName": "",
        "ImportedCertificateIssuer": "",
        "ImportedCertificateSubject": ""
    },
    "KeyServerRedundancyReq": false,
    "PrimaryKeyServerAddress": null,
    "PrimaryKeyServerPort": null,
    "SecondaryKeyServerAddress": null,
    "SecondaryKeyServerPort": null
}